pytsa_ais-2.3.14.dist-info/METADATA
pytsa_ais-2.3.14.dist-info/WHEEL
pytsa_ais-2.3.14.dist-info/licenses/LICENSE
pytsa/visualization/misc.py
pytsa/visualization/__init__.py
pytsa/visualization/ecdf.py
pytsa/tsea/__init__.py
pytsa/tsea/split.py
pytsa/tsea/targetship.py
pytsa/tsea/search_agent.py
pytsa/decoder/filedescriptor.py
pytsa/decoder/__init__.py
pytsa/decoder/ais_decoder.py
pytsa/__init__.py
pytsa/logger.py
pytsa/utils.pyi
pytsa/structs.py
pytsa/utils.py
pytsa/py.typed
pytsa/trajectories/__init__.py
pytsa/trajectories/rules.py
pytsa/trajectories/inspect.py
pytsa/data/__init__.py
pytsa/data/geometry/norway.json
pytsa/data/geometry/netherlands_detailed.json
pytsa/data/geometry/__init__.py
pytsa/data/geometry/denmark.json
pytsa/data/geometry/germany.json
pytsa/data/geometry/sweden.json
pytsa/data/quantiles/quantiles.pkl
pytsa/data/quantiles/__init__.py
pytsa/data/quantiles/independent/iquantiles.pkl
pytsa/_pytsa_compiled.cpython-311-darwin.so
pytsa_ais-2.3.14.dist-info/RECORD
