Metadata-Version: 2.3
Name: pytsa-ais
Version: 2.3.14
Classifier: Programming Language :: Python :: 3
Classifier: License :: OSI Approved :: GNU General Public License v3 or later (GPLv3+)
Classifier: Operating System :: OS Independent
Requires-Dist: sentinel >=1.0.0
Requires-Dist: pyais >=2.6.2
Requires-Dist: numpy >=1.19
Requires-Dist: matplotlib >=3.5.3
Requires-Dist: ciso8601 >=2.3.1
Requires-Dist: geopandas >=0.10.2
Requires-Dist: pandas >=1.3.4
Requires-Dist: scipy >=1.7.1
Requires-Dist: utm >=0.7.0
Requires-Dist: vincenty >=0.1.4
Requires-Dist: tomli >=2.0.1
Requires-Dist: osm2geojson >=0.2.5
License-File: LICENSE
Summary: Toolbox for extracting trajectories and monitoring vessels from raw AIS records.
Author: Niklas Paulig
Author-email: niklas.paulig@tu-dresden.de
Requires-Python: >=3.10
Project-URL: homepage, https://github.com/nikpau/pytsa
Project-URL: issues, https://github.com/nikpau/pytsa/issues
